[
  {
    "time": "2025-06-02 22:23",
    "text": "لقبييييييييييرتةاة"
  },
  {
    "time": "2025-06-03 12:10",
    "text": "التص"
  },
  {
    "time": "2025-06-03 13:28",
    "text": "لاهلخبت توتمخ شبياعؤ ةاخىناو  ر خيبرو ويسوبسخوؤ  لاخهةلىةه ةبلهلاة"
  },
  {
    "time": "2025-06-03 13:28",
    "text": "لاهلخبت توتمخ شبياعؤ ةاخىناو  ر خيبرو ويسوبسخوؤ  لاخهةلىةه"
  },
  {
    "time": "2025-06-04 16:30",
    "text": "السلام عليكم"
  },
  {
    "time": "2025-06-04 16:32",
    "text": "الان سوف نبدا في عمليه الترجمه"
  },
  {
    "time": "2025-06-04 16:33",
    "text": "حارس"
  },
  {
    "time": "2025-06-04 16:39",
    "text": "لتلاتو"
  },
  {
    "time": "2025-06-04 16:40",
    "text": "مرحبا"
  },
  {
    "time": "2025-06-04 16:53",
    "text": "مرحبا"
  },
  {
    "time": "2025-06-08 18:54",
    "text": ""
  },
  {
    "time": "2025-06-09 00:59",
    "text": "السلام عليكم"
  },
  {
    "time": "2025-06-09 23:37",
    "text": "السلام"
  },
  {
    "time": "2025-06-09 23:38",
    "text": "مرحبا"
  },
  {
    "time": "2025-06-13 18:40",
    "text": "السلام عليكم"
  },
  {
    "time": "2025-06-13 18:49",
    "text": "السلام عليكم"
  },
  {
    "time": "2025-06-25 23:28",
    "text": "الس"
  },
  {
    "time": "2025-06-25 23:29",
    "text": "كيف حالك"
  },
  {
    "time": "2025-06-25 23:29",
    "text": "كيف حالك"
  },
  {
    "time": "2025-06-27 23:17",
    "text": "فتح  وكان يطالعنى سؤال ترددذين صادفتهم  ومن الذين لمماؤلهم  ماسر إقبال الناس علىشديدا  وما مر تكرر نشرها فىداته العلنية وطبعاته المزورة اللغات عرفت منها التركيةأخبرنى علماء من تركيا والهند"
  },
  {
    "time": "2025-06-28 00:57",
    "text": "كيف حالك"
  },
  {
    "time": "2025-06-28 00:58",
    "text": "الجمهورية الجزائرية الدبمقراطية الشعبيةالرقم التاريخالدائرة اإغاريةصريسح باللسسعكل تصريح فيه زياد أو شطب لايكون صالحا ل كان اليلدالمينةبع مركتي ذات المراصفات الليلصيف الزنلسلى في اللا الميكلء الطالةعدد المقاد جملة المولة الررفصةلميدة سلة أول اتتمال في السيربل السائق كان اليلدبأن هذه المركبة مازالت مطابقة لآخر محضر للقبول صادر من مصلحة المناجم"
  },
  {
    "time": "2025-06-28 01:04",
    "text": "السلام عليكم"
  },
  {
    "time": "2025-06-28 01:05",
    "text": "الجمهورية الجزائرية الدبمقراطية الشعبيةالرقم التاريخصريسح باللسسعأكل تصريج فيه زياد أو شطب ل يكون صالهاأنا اليد  الجسية المينأصرح بع مركتي ذات المراصفات اللي لصيف لطرلقم التلسلى ف الطرا اليكل الطافةالقوه عدد المقاد جملة الحولة الررفصةالحمولة اميد سلة أول اتتمال في السيررقم التسجيل السابق رقم التسجيل العالىإلى السيداقاةالاسوو الف انا كما لشهد أن هذ المركبة مات مطيقة أآخر معضر ابول صادر من مصلحة المناجم"
  },
  {
    "time": "2025-06-28 01:07",
    "text": "مرحبا"
  }
]